bsecure_client/__init__.py
bsecure_client/api/__init__.py
bsecure_client/api/asset_api.py
bsecure_client/api/base.py
bsecure_client/api/contractor_api.py
bsecure_client/api/integration_api.py
bsecure_client/api/place_api.py
bsecure_client/api/routing_api.py
bsecure_client/api/types.py
bsecure_client/client.py
bsecure_client/exceptions.py
bsecure_client/queries.py
bsecure_client/utils.py
bsecure_client-0.2.9.0.dist-info/METADATA
bsecure_client-0.2.9.0.dist-info/WHEEL
bsecure_client-0.2.9.0.dist-info/RECORD
