Metadata-Version: 2.4
Name: bsecure-client
Version: 0.2.9.0
Summary: BeSecure Client
License: MIT
Author: Jarek Głowacki
Author-email: jarekwg@gmail.com
Requires-Python: >=3.9,<4.0
Classifier: Development Status :: 3 - Alpha
Classifier: Intended Audience :: Developers
Classifier: License :: OSI Approved :: MIT License
Classifier: Natural Language :: English
Classifier: Operating System :: OS Independent
Classifier: Programming Language :: Python
Classifier: Programming Language :: Python :: 3
Classifier: Programming Language :: Python :: 3.9
Classifier: Programming Language :: Python :: 3.10
Classifier: Programming Language :: Python :: 3.11
Classifier: Programming Language :: Python :: 3.12
Classifier: Programming Language :: Python :: 3.13
Classifier: Programming Language :: Python :: 3.14
Classifier: Programming Language :: Python :: 3.7
Requires-Dist: pydantic (>=2.5.0,<3.0.0)
Requires-Dist: requests (>=2.0.0,<3.0.0)
